evemap/__init__.py
evemap/admin.py
evemap/api.py
evemap/app_settings.py
evemap/apps.py
evemap/auth_hooks.py
evemap/models.py
evemap/tasks.py
evemap/urls.py
evemap/views.py
evemap/data/regions.geojson
evemap/migrations/__init__.py
evemap/static/evemap/frontend/index.html
evemap/static/evemap/frontend/.vite/manifest.json
evemap/static/evemap/frontend/assets/index-CDxsRY9J.css
evemap/static/evemap/frontend/assets/index-DQAwHDEy.js
evemap/static/evemap/frontend/assets/index-ENRWoX7g.js
evemap/static/evemap/geospatial/region_stargates_lines.geojson
evemap/static/evemap/geospatial/solar_systems.geojson
evemap/static/evemap/geospatial/stargates_lines.geojson
evemap/templates/evemap/base.html
evemap/templates/evemap/index.html
evemap/templatetags/__init__.py
evemap/templatetags/render_vite_bundle.py
evemap/tests/__init__.py
evemap/tests/test_tasks.py
evemap/utils/geospatial.py
evemap/utils/graph.py
evemap-0.0.0b5.dist-info/licenses/LICENSE
evemap-0.0.0b5.dist-info/WHEEL
evemap-0.0.0b5.dist-info/METADATA
evemap-0.0.0b5.dist-info/RECORD
