Metadata-Version: 2.4
Name: evemap
Version: 0.0.0b5
Summary: Example plugin app for Alliance Auth.
Author-email: Cunning <ryan.cunning@gmail.com>
Requires-Python: >=3.8
Classifier: Environment :: Web Environment
Classifier: Framework :: Django
Classifier: Framework :: Django :: 4.0
Classifier: Framework :: Django :: 4.2
Classifier: Intended Audience :: Developers
Classifier: License :: OSI Approved :: MIT License
Classifier: Operating System :: OS Independent
Classifier: Programming Language :: Python
Classifier: Programming Language :: Python :: 3.8
Classifier: Programming Language :: Python :: 3.9
Classifier: Programming Language :: Python :: 3.10
Classifier: Programming Language :: Python :: 3.11
Classifier: Topic :: Internet :: WWW/HTTP
Classifier: Topic :: Internet :: WWW/HTTP :: Dynamic Content
License-File: LICENSE
Requires-Dist: allianceauth>=3
Requires-Dist: django-eveuniverse==1.5.7
Requires-Dist: django-ninja==1.4.3
Requires-Dist: geojson==3.2.0
Requires-Dist: shapely==2.1.1
Project-URL: Changelog, https://gitlab.com/cunningdesigns/evemap/-/blob/main/CHANGELOG.md
Project-URL: Documentation, https://gitlab.com/cunningdesigns/evemap/-/tree/main/docs?ref_type=heads
Project-URL: Homepage, https://gitlab.com/cunningdesigns/evemap
Project-URL: Source, https://gitlab.com/cunningdesigns/evemap
Project-URL: Tracker, https://gitlab.com/cunningdesigns/evemap/-/issues
